flaightkitplugins_pod-0.1.0-py2.7-nspkg.pth
flytekitplugins/pod/__init__.py
flytekitplugins/pod/task.py
flaightkitplugins_pod-0.1.0.dist-info/METADATA
flaightkitplugins_pod-0.1.0.dist-info/WHEEL
flaightkitplugins_pod-0.1.0.dist-info/namespace_packages.txt
flaightkitplugins_pod-0.1.0.dist-info/top_level.txt
flaightkitplugins_pod-0.1.0.dist-info/RECORD
